MANIFEST.in
res_config_user_view.xml
setup.py
./__init__.py
./__openerp__.py
./google_docs.py
i18n/ar.po
i18n/cs.po
i18n/de.po
i18n/es.po
i18n/fr.po
i18n/google_docs.pot
i18n/hr.po
i18n/hu.po
i18n/it.po
i18n/ln.po
i18n/mk.po
i18n/mn.po
i18n/nl.po
i18n/pl.po
i18n/pt.po
i18n/pt_BR.po
i18n/ro.po
i18n/ru.po
i18n/sl.po
i18n/sv.po
i18n/tr.po
i18n/zh_CN.po
openerp_google_docs.egg-info/PKG-INFO
openerp_google_docs.egg-info/SOURCES.txt
openerp_google_docs.egg-info/dependency_links.txt
openerp_google_docs.egg-info/requires.txt
openerp_google_docs.egg-info/top_level.txt
security/ir.model.access.csv
static/src/js/gdocs.js
static/src/xml/gdocs.xml